README.txt
setup.cfg
setup.py
cs/__init__.py
cs.editabletagline.egg-info/PKG-INFO
cs.editabletagline.egg-info/SOURCES.txt
cs.editabletagline.egg-info/dependency_links.txt
cs.editabletagline.egg-info/entry_points.txt
cs.editabletagline.egg-info/namespace_packages.txt
cs.editabletagline.egg-info/not-zip-safe
cs.editabletagline.egg-info/requires.txt
cs.editabletagline.egg-info/top_level.txt
cs/editabletagline/__init__.py
cs/editabletagline/configure.zcml
cs/editabletagline/interfaces.py
cs/editabletagline/permissions.zcml
cs/editabletagline/profiles.zcml
cs/editabletagline/rebuild_i18n.sh
cs/editabletagline/tagline.pt
cs/editabletagline/tagline.py
cs/editabletagline/tests.py
cs/editabletagline/upgrades.py
cs/editabletagline/locales/cs.editabletagline-manual.pot
cs/editabletagline/locales/cs.editabletagline.pot
cs/editabletagline/locales/es/LC_MESSAGES/cs.editabletagline.po
cs/editabletagline/locales/eu/LC_MESSAGES/cs.editabletagline.po
cs/editabletagline/profiles/default/browserlayer.xml
cs/editabletagline/profiles/default/controlpanel.xml
cs/editabletagline/profiles/default/metadata.xml
cs/editabletagline/profiles/default/propertiestool.xml
cs/editabletagline/profiles/default/rolemap.xml
cs/editabletagline/profiles/default/viewlets.xml
docs/HISTORY.txt
docs/INSTALL.txt
docs/LICENSE.GPL
docs/LICENSE.txt