Metadata-Version: 1.1
Name: cs.editabletagline
Version: 2.0.1
Summary: A simple package providing a editable tagline for Plone
Home-page: http://github.com/codesyntax/cs.editabletagline
Author: Lur Ibargutxi
Author-email: libargutxi@codesyntax.com
License: GPL
Keywords: plone viewlet tagline
Platform: UNKNOWN
Classifier: Framework :: Plone
Classifier: Programming Language :: Python
